batch_create_invoices-1.0.0.dist-info/DESCRIPTION.rst
batch_create_invoices-1.0.0.dist-info/METADATA
batch_create_invoices-1.0.0.dist-info/RECORD
batch_create_invoices-1.0.0.dist-info/WHEEL
batch_create_invoices-1.0.0.dist-info/metadata.json
batch_create_invoices-1.0.0.dist-info/top_level.txt
mock_invoices/__init__.py
mock_invoices/__main__.py
mock_invoices/batch_create_invoice.py
mock_invoices/config.py
mock_invoices/input_util.py
mock_invoices/invoice.py
test_util/__init__.py
test_util/batch_create_invoice.py
test_util/config.py
test_util/input_util.py
test_util/invoice.py
