Metadata-Version: 2.0
Name: batch-create-invoices
Version: 1.0.0
Summary: A util for batch create mock invoice for tradeshift.
Home-page: https://github.com/Lewis-ZhangHP/structures_algorithms
Author: Lewis Zhang
Author-email: 244563813@qq.com
License: UNKNOWN
Platform: UNKNOWN
Classifier: Programming Language :: Python :: 3
Classifier: License :: OSI Approved :: MIT License
Classifier: Operating System :: OS Independent
Requires-Dist: requests
